LICENSE
spellsync/__init__.py
spellsync/dictionary/__init__.py
spellsync/dictionary/apple_spell.py
spellsync/dictionary/aspell.py
spellsync/dictionary/base.py
spellsync/dictionary/common.py
spellsync/dictionary/mac_firefox.py
spellsync/dictionary/mac_office.py
spellsync/dictionary/mac_thunderbird.py
spellsync/dictionary/neovim.py
spellsync/main.py
spellsync-0.2.0.dist-info/LICENSE
spellsync-0.2.0.dist-info/METADATA
spellsync-0.2.0.dist-info/WHEEL
spellsync-0.2.0.dist-info/entry_points.txt
spellsync-0.2.0.dist-info/RECORD
