Metadata-Version: 2.1
Name: spellsync
Version: 0.2.0
Summary: Synchronise personal spelling dictionaries across applications
Home-page: https://github.com/pneff/SpellSync
License: MIT
Author: Patrice Neff
Author-email: mail@patrice.ch
Requires-Python: >=3.9,<4.0
Classifier: Development Status :: 3 - Alpha
Classifier: Environment :: Console
Classifier: License :: OSI Approved :: BSD License
Classifier: License :: OSI Approved :: MIT License
Classifier: Programming Language :: Python :: 3
Classifier: Programming Language :: Python :: 3.9
Classifier: Programming Language :: Python :: 3.10
Classifier: Programming Language :: Python :: 3.11
Classifier: Topic :: Text Editors
Classifier: Topic :: Utilities
Requires-Dist: click (>=8.0.3,<9.0.0)
Requires-Dist: xdg (>=5.1.1,<6.0.0)
Project-URL: Repository, https://github.com/pneff/SpellSync
